takahom/__init__.py
takahom/py.typed
takahom/client/__init__.py
takahom/client/client.py
takahom/client/client_browser.py
takahom/common/__init__.py
takahom/common/common_ctts_ytb.py
takahom/common/common_etc.py
takahom/common/common_imports.py
takahom/common/common_util.py
takahom/common/down_paras.py
takahom/common/down_request.py
takahom/common/down_result.py
takahom/common/entity.py
takahom/common/etc_util.py
takahom/common/firefox_util.py
takahom/common/ytb_util.py
takahom/etc/__init__.py
takahom/server/__init__.py
takahom/server/__main__.py
takahom/server/server.py
takahom/server/server_base_a.py
takahom/server/server_base_c_download.py
takahom/server/server_base_d.py
takahom/server/server_base_e.py
takahom/server/server_base_web.py
takahom/server/server_config.py
takahom/server/server_imports.py
takahom/server/server_index.py
takahom/server/server_ytb_demo.py
takahom/server/server_ytb_util.py
takahom-0.5.4.dist-info/METADATA
takahom-0.5.4.dist-info/WHEEL
takahom-0.5.4.dist-info/top_level.txt
takahom-0.5.4.dist-info/RECORD
