Metadata-Version: 2.1
Name: takahom
Version: 0.5.4
Summary: a youtube video downloader tool, based on yt-dlp project
Author-email: dknova <dikisite@outlook.com>
License: LGPL
Classifier: Programming Language :: Python :: 3
Classifier: License :: OSI Approved :: MIT License
Classifier: Operating System :: OS Independent
Requires-Python: >=3.10
Requires-Dist: numpy ==1.26.2
Requires-Dist: ipython
Requires-Dist: dknovautils ==0.2.6
